GuffBotPackage/__init__.py
GuffBotPackage-1.0.2.dist-info/LICENSE
GuffBotPackage-1.0.2.dist-info/METADATA
GuffBotPackage-1.0.2.dist-info/WHEEL
GuffBotPackage-1.0.2.dist-info/entry_points.txt
GuffBotPackage-1.0.2.dist-info/top_level.txt
GuffBotPackage-1.0.2.dist-info/RECORD
