Metadata-Version: 2.1
Name: GuffBotPackage
Version: 1.0.2
Summary: Guff Bot Package Made By NotEason.
Home-page: https://tiktok.com/@noteason
Author: noteason
Author-email: tiktoknoteason@gmail.com
License: MIT
Platform: UNKNOWN
Classifier: License :: OSI Approved :: MIT License
Classifier: Programming Language :: Python :: 3
Classifier: Programming Language :: Python :: 3.7
Requires-Dist: requests
